gravityRecorder/__init__.py
gravityRecorder/functions.py
gravityRecorder/main.py
gravityRecorder/settings.py
gravityRecorder/alerts/__init__.py
gravityRecorder/alerts/alert_funcs.py
gravityRecorder/alerts/settings.py
gravityRecorder/tests/__init__.py
gravityRecorder/tests/functions_test.py
gravityRecorder/tests/main_test.py
gravityRecorder/tests/test_objects.py
gravityRecorder-1.8.51.dist-info/METADATA
gravityRecorder-1.8.51.dist-info/WHEEL
gravityRecorder-1.8.51.dist-info/top_level.txt
gravityRecorder-1.8.51.dist-info/RECORD
