Metadata-Version: 2.1
Name: gravityRecorder
Version: 1.8.51
Summary: GravityRecorder - фреймворк для работы с БД в проекте Gravity
Home-page: UNKNOWN
Author: Arthur
Author-email: ksmdrmvstchny@gmail.com
License: MIT
Platform: UNKNOWN
